exotic/__init__.py
exotic/animate.py
exotic/exotic.py
exotic/exotic_gui.py
exotic/inputs.py
exotic/output_files.py
exotic/plate_status.py
exotic/plots.py
exotic/utils.py
exotic/version.py
exotic/api/__init__.py
exotic/api/colab.py
exotic/api/elca.py
exotic/api/ephemeris.py
exotic/api/ew.py
exotic/api/filters.py
exotic/api/gael_ld.py
exotic/api/joint_fitter.py
exotic/api/ld.py
exotic/api/nbody.py
exotic/api/nea.py
exotic/api/nested_linear_fitter.py
exotic/api/output_aavso.py
exotic/api/plate_solution.py
exotic/api/plotting.py
exotic/api/rv_archive.py
exotic/api/rv_fitter.py
exotic/api/versioning.py
exotic-4.3.1.dist-info/LICENSE
exotic-4.3.1.dist-info/METADATA
exotic-4.3.1.dist-info/WHEEL
exotic-4.3.1.dist-info/entry_points.txt
exotic-4.3.1.dist-info/top_level.txt
exotic-4.3.1.dist-info/RECORD
