Metadata-Version: 2.2
Name: exotic
Version: 4.3.1
Summary: EXOTIC: EXOplanet Transit Interpretation Code
Home-page: https://github.com/rzellem/EXOTIC
Download-URL: https://github.com/rzellem/EXOTIC/releases/latest
Author: Exoplanet Watch at NASA JPL
Author-email: exoplanetwatch@jpl.nasa.gov
License: Proprietary -- Copyright (c) 2019-present, California Institute of Technology.
Project-URL: Documentation, https://github.com/rzellem/EXOTIC/wiki
Project-URL: Site, https://exoplanets.nasa.gov/exoplanet-watch
Project-URL: Source, https://github.com/rzellem/EXOTIC
Project-URL: Tracker, https://github.com/rzellem/EXOTIC/issues
Project-URL: Download, https://github.com/rzellem/EXOTIC/releases/latest
Keywords: nasa,jpl,exoplanet,transit,citizen science,astronomy,bayesian,nested-sampler
Classifier: Development Status :: 5 - Production/Stable
Classifier: Intended Audience :: End Users/Desktop
Classifier: Intended Audience :: Science/Research
Classifier: License :: Other/Proprietary License
Classifier: Programming Language :: Python
Classifier: Programming Language :: Python :: 3
Classifier: Programming Language :: Python :: 3.10
Classifier: Programming Language :: Python :: Implementation :: CPython
Classifier: Programming Language :: Python :: Implementation :: PyPy
Classifier: Topic :: Scientific/Engineering :: Astronomy
Requires-Python: >=3.10
License-File: LICENSE
Requires-Dist: astroalign~=2.6.0
Requires-Dist: astropy~=6.1
Requires-Dist: astroquery~=0.4.7
Requires-Dist: barycorrpy~=0.4.4
Requires-Dist: colour_demosaicing~=0.2.6
Requires-Dist: dynesty~=1.2.3; platform_system == "Windows"
Requires-Dist: holoviews~=1.19.1
Requires-Dist: importlib-metadata>=3.6; python_version <= "3.7"
Requires-Dist: imreg_dft~=2.0.0
Requires-Dist: LDTk~=1.8.4
Requires-Dist: lmfit~=1.3.2
Requires-Dist: matplotlib~=3.9.2
Requires-Dist: numba~=0.59.1
Requires-Dist: numpy~=1.26.4
Requires-Dist: pandas~=2.2.3
Requires-Dist: panel~=1.5.2
Requires-Dist: photutils~=2.0.0
Requires-Dist: pylightcurve<5,>=4.0.1
Requires-Dist: python_dateutil~=2.9
Requires-Dist: python_version
Requires-Dist: pyvo~=1.5.3
Requires-Dist: rebound~=4.4.3
Requires-Dist: requests~=2.32.3
Requires-Dist: scipy~=1.14.1
Requires-Dist: scikit-image~=0.24.0
Requires-Dist: statsmodels~=0.14.4
Requires-Dist: tenacity~=9.0
Requires-Dist: ultranest~=3.6.5; platform_system != "Windows"
Dynamic: download-url
